<?xml version="1.0" encoding="utf-8" ?>
<Defs>

  <IncidentDef>
    <defName>FRS_PR_BaseAbandoned</defName>
    <label>Faction base abandoned</label>
    <category>Misc</category>
    <targetTags>
      <li>World</li>
    </targetTags>
    <workerClass>RedScare.IncidentWorker_BaseAbandoned</workerClass>
    <baseChance>0</baseChance>
    <minRefireDays>0</minRefireDays>
    <letterDef>PositiveEvent</letterDef>
    <letterLabel>{FACTION_name}'s base abandoned</letterLabel>
    <letterText>{FACTION_name}'s base abandoned.</letterText>
  </IncidentDef>
  
  
  <IncidentDef>
    <defName>FRS_PR_SmallBaseSpawned</defName>
    <label>small base spawned</label>
    <category>ThreatSmall</category>
    <targetTags>
      <li>World</li>
    </targetTags>
    <workerClass>RedScare.IncidentWorker_FactionBaseSpawned</workerClass>
    <baseChance>0</baseChance>
    <minRefireDays>0</minRefireDays>
    <letterDef>ThreatSmall</letterDef>
    <letterLabel>small base spawned</letterLabel>
    <letterText>small base spawned</letterText>
  </IncidentDef>
  
  <IncidentDef>
    <defName>FRS_PR_BigBaseSpawned</defName>
    <label>big base spawned</label>
    <category>ThreatBig</category>
    <targetTags>
      <li>World</li>
    </targetTags>
    <workerClass>RedScare.IncidentWorker_FactionBaseSpawned</workerClass>
    <baseChance>0</baseChance>
    <minRefireDays>0</minRefireDays>
    <letterDef>ThreatBig</letterDef>
    <letterLabel>big base spawned</letterLabel>
    <letterText>big base spawned</letterText>
  </IncidentDef>
</Defs>